sketchit/__init__.py
sketchit/__main__.py
sketchit/draw.py
sketchme-1.13.dist-info/METADATA
sketchme-1.13.dist-info/WHEEL
sketchme-1.13.dist-info/entry_points.txt
sketchme-1.13.dist-info/top_level.txt
sketchme-1.13.dist-info/RECORD
