Metadata-Version: 2.1
Name: sketchme
Version: 1.13
Summary: Converts a real world images into Pencil SKETCH
Home-page: UNKNOWN
Author: Bhavika Tambi
Author-email: tambibhavika2000@gmail.com
License: MIT
Platform: UNKNOWN
Classifier: License :: OSI Approved :: MIT License
Classifier: Programming Language :: Python :: 3.6
